collective/html2blocks/__init__.py
collective/html2blocks/_types.py
collective/html2blocks/cli.py
collective/html2blocks/converter.py
collective/html2blocks/logger.py
collective/html2blocks/registry.py
collective/html2blocks/blocks/__init__.py
collective/html2blocks/blocks/image.py
collective/html2blocks/blocks/table.py
collective/html2blocks/blocks/video.py
collective/html2blocks/blocks/iframe/__init__.py
collective/html2blocks/blocks/iframe/soundcloud.py
collective/html2blocks/blocks/iframe/youtube.py
collective/html2blocks/blocks/slate/__init__.py
collective/html2blocks/blocks/slate/parser.py
collective/html2blocks/commands/__init__.py
collective/html2blocks/commands/convert.py
collective/html2blocks/commands/info.py
collective/html2blocks/commands/server.py
collective/html2blocks/services/__init__.py
collective/html2blocks/services/healthcheck.py
collective/html2blocks/services/html.py
collective/html2blocks/services/info.py
collective/html2blocks/utils/__init__.py
collective/html2blocks/utils/blocks.py
collective/html2blocks/utils/generator.py
collective/html2blocks/utils/inline.py
collective/html2blocks/utils/markup.py
collective/html2blocks/utils/slate.py
collective_html2blocks-1.0.0a2.dist-info/METADATA
collective_html2blocks-1.0.0a2.dist-info/WHEEL
collective_html2blocks-1.0.0a2.dist-info/entry_points.txt
collective_html2blocks-1.0.0a2.dist-info/RECORD
